main.py
iflow_mcp_remyguercio_tailscale_mcp_echo-0.1.1.dist-info/licenses/LICENSE
iflow_mcp_remyguercio_tailscale_mcp_echo-0.1.1.dist-info/METADATA
iflow_mcp_remyguercio_tailscale_mcp_echo-0.1.1.dist-info/WHEEL
iflow_mcp_remyguercio_tailscale_mcp_echo-0.1.1.dist-info/entry_points.txt
iflow_mcp_remyguercio_tailscale_mcp_echo-0.1.1.dist-info/top_level.txt
iflow_mcp_remyguercio_tailscale_mcp_echo-0.1.1.dist-info/RECORD
