Metadata-Version: 2.4
Name: iflow-mcp-remyguercio-tailscale-mcp-echo
Version: 0.1.1
Summary: This MCP returns the identity of the currently logged in user.
Requires-Python: >=3.11
License-File: LICENSE
Requires-Dist: fastmcp>=2.3.3
Requires-Dist: starlette>=0.46.2
Dynamic: license-file
